homeconnect_websocket/__init__.py
homeconnect_websocket/appliance.py
homeconnect_websocket/const.py
homeconnect_websocket/description_parser.py
homeconnect_websocket/entities.py
homeconnect_websocket/errors.py
homeconnect_websocket/hc_socket.py
homeconnect_websocket/helpers.py
homeconnect_websocket/message.py
homeconnect_websocket/session.py
homeconnect_websocket/testutils.py
homeconnect_websocket-1.4.7.dist-info/METADATA
homeconnect_websocket-1.4.7.dist-info/WHEEL
homeconnect_websocket-1.4.7.dist-info/entry_points.txt
homeconnect_websocket-1.4.7.dist-info/top_level.txt
homeconnect_websocket-1.4.7.dist-info/RECORD
