Metadata-Version: 2.4
Name: homeconnect_websocket
Version: 1.4.7
Summary: Home Connect Websocket API
Author: chris-mc1
Project-URL: Homepage, https://github.com/chris-mc1/homeconnect_websocket
Project-URL: Issues, https://github.com/chris-mc1/homeconnect_websocket/issues
Classifier: Programming Language :: Python :: 3
Classifier: Programming Language :: Python :: 3.13
Classifier: Operating System :: OS Independent
Requires-Python: >=3.13
Requires-Dist: aiohttp>=3.10
Requires-Dist: xmltodict>=0.13.0
Requires-Dist: pycryptodome>=3.21.0
